{
  "id": "AkUR27wtaxs",
  "created_at": "2016-04-26T14:44:23-04:00",
  "updated_at": "2019-09-21T01:07:15-04:00",
  "width": 4738,
  "height": 3159,
  "color": "#FFA790",
  "description": "Högakustenbron in the pink and the clouds",
  "alt_description": "grey full-suspension bridge photography during daytime",
  "urls": {
    "raw": "https://images.unsplash.com/photo-1461696114087-397271a7aedc?ixlib=rb-1.2.1&ixid=eyJhcHBfaWQiOjkzMTQ3fQ",
    "full": "https://images.unsplash.com/photo-1461696114087-397271a7aedc?ixlib=rb-1.2.1&q=85&fm=jpg&crop=entropy&cs=srgb&ixid=eyJhcHBfaWQiOjkzMTQ3fQ",
    "regular": "https://images.unsplash.com/photo-1461696114087-397271a7aedc?ixlib=rb-1.2.1&q=80&fm=jpg&crop=entropy&cs=tinysrgb&w=1080&fit=max&ixid=eyJhcHBfaWQiOjkzMTQ3fQ",
    "small": "https://images.unsplash.com/photo-1461696114087-397271a7aedc?ixlib=rb-1.2.1&q=80&fm=jpg&crop=entropy&cs=tinysrgb&w=400&fit=max&ixid=eyJhcHBfaWQiOjkzMTQ3fQ",
    "thumb": "https://images.unsplash.com/photo-1461696114087-397271a7aedc?ixlib=rb-1.2.1&q=80&fm=jpg&crop=entropy&cs=tinysrgb&w=200&fit=max&ixid=eyJhcHBfaWQiOjkzMTQ3fQ"
  },
  "links": {
    "self": "https://api.unsplash.com/photos/AkUR27wtaxs",
    "html": "https://unsplash.com/photos/AkUR27wtaxs",
    "download": "https://unsplash.com/photos/AkUR27wtaxs/download",
    "download_location": "https://api.unsplash.com/photos/AkUR27wtaxs/download"
  },
  "categories": [],
  "likes": 1352,
  "liked_by_user": false,
  "current_user_collections": [],
  "user": {
    "id": "46rKBE69V4I",
    "updated_at": "2019-09-24T15:50:30-04:00",
    "username": "andersjilden",
    "name": "Anders Jildén",
    "first_name": "Anders",
    "last_name": "Jildén",
    "twitter_username": "AndersJilden",
    "portfolio_url": "http://www.andersjilden.com",
    "bio": "Passionate about design and photography.\r\nCurious in general. Need other resolutions? Send me a DM.\r\n\r\nInstagram: instagram.com/andersjildenphotography",
    "location": "Stockholm, Sweden",
    "links": {
      "self": "https://api.unsplash.com/users/andersjilden",
      "html": "https://unsplash.com/@andersjilden",
      "photos": "https://api.unsplash.com/users/andersjilden/photos",
      "likes": "https://api.unsplash.com/users/andersjilden/likes",
      "portfolio": "https://api.unsplash.com/users/andersjilden/portfolio",
      "following": "https://api.unsplash.com/users/andersjilden/following",
      "followers": "https://api.unsplash.com/users/andersjilden/followers"
    },
    "profile_image": {
      "small": "https://images.unsplash.com/profile-1544366928427-937b7f3674c0?ixlib=rb-1.2.1&q=80&fm=jpg&crop=faces&cs=tinysrgb&fit=crop&h=32&w=32",
      "medium": "https://images.unsplash.com/profile-1544366928427-937b7f3674c0?ixlib=rb-1.2.1&q=80&fm=jpg&crop=faces&cs=tinysrgb&fit=crop&h=64&w=64",
      "large": "https://images.unsplash.com/profile-1544366928427-937b7f3674c0?ixlib=rb-1.2.1&q=80&fm=jpg&crop=faces&cs=tinysrgb&fit=crop&h=128&w=128"
    },
    "instagram_username": "andersjildenphotography",
    "total_collections": 0,
    "total_likes": 18,
    "total_photos": 34,
    "accepted_tos": false
  }
}
