{
  "id": "Fb_-lr104Jw",
  "created_at": "2018-02-19T17:29:55-05:00",
  "updated_at": "2019-09-14T01:05:01-04:00",
  "width": 4905,
  "height": 2759,
  "color": "#1C1823",
  "description": "Kinda weird when you look up and all you can see is buildings. I’m not sure if it’s intimidating or invigorating.",
  "alt_description": "high-rise building",
  "urls": {
    "raw": "https://images.unsplash.com/photo-1519079286144-72c398115265?ixlib=rb-1.2.1&ixid=eyJhcHBfaWQiOjkzMTQ3fQ",
    "full": "https://images.unsplash.com/photo-1519079286144-72c398115265?ixlib=rb-1.2.1&q=85&fm=jpg&crop=entropy&cs=srgb&ixid=eyJhcHBfaWQiOjkzMTQ3fQ",
    "regular": "https://images.unsplash.com/photo-1519079286144-72c398115265?ixlib=rb-1.2.1&q=80&fm=jpg&crop=entropy&cs=tinysrgb&w=1080&fit=max&ixid=eyJhcHBfaWQiOjkzMTQ3fQ",
    "small": "https://images.unsplash.com/photo-1519079286144-72c398115265?ixlib=rb-1.2.1&q=80&fm=jpg&crop=entropy&cs=tinysrgb&w=400&fit=max&ixid=eyJhcHBfaWQiOjkzMTQ3fQ",
    "thumb": "https://images.unsplash.com/photo-1519079286144-72c398115265?ixlib=rb-1.2.1&q=80&fm=jpg&crop=entropy&cs=tinysrgb&w=200&fit=max&ixid=eyJhcHBfaWQiOjkzMTQ3fQ"
  },
  "links": {
    "self": "https://api.unsplash.com/photos/Fb_-lr104Jw",
    "html": "https://unsplash.com/photos/Fb_-lr104Jw",
    "download": "https://unsplash.com/photos/Fb_-lr104Jw/download",
    "download_location": "https://api.unsplash.com/photos/Fb_-lr104Jw/download"
  },
  "categories": [],
  "likes": 14,
  "liked_by_user": false,
  "current_user_collections": [],
  "user": {
    "id": "LdPisKAiXDc",
    "updated_at": "2019-09-24T02:39:33-04:00",
    "username": "joeypilgrim",
    "name": "Joey Pilgrim",
    "first_name": "Joey",
    "last_name": "Pilgrim",
    "twitter_username": null,
    "portfolio_url": null,
    "bio": "I love doing what I do.",
    "location": "Alberta",
    "links": {
      "self": "https://api.unsplash.com/users/joeypilgrim",
      "html": "https://unsplash.com/@joeypilgrim",
      "photos": "https://api.unsplash.com/users/joeypilgrim/photos",
      "likes": "https://api.unsplash.com/users/joeypilgrim/likes",
      "portfolio": "https://api.unsplash.com/users/joeypilgrim/portfolio",
      "following": "https://api.unsplash.com/users/joeypilgrim/following",
      "followers": "https://api.unsplash.com/users/joeypilgrim/followers"
    },
    "profile_image": {
      "small": "https://images.unsplash.com/profile-1493846031863-9ecb8cea5b2b?ixlib=rb-1.2.1&q=80&fm=jpg&crop=faces&cs=tinysrgb&fit=crop&h=32&w=32",
      "medium": "https://images.unsplash.com/profile-1493846031863-9ecb8cea5b2b?ixlib=rb-1.2.1&q=80&fm=jpg&crop=faces&cs=tinysrgb&fit=crop&h=64&w=64",
      "large": "https://images.unsplash.com/profile-1493846031863-9ecb8cea5b2b?ixlib=rb-1.2.1&q=80&fm=jpg&crop=faces&cs=tinysrgb&fit=crop&h=128&w=128"
    },
    "instagram_username": "joeypilgrim",
    "total_collections": 0,
    "total_likes": 3,
    "total_photos": 7,
    "accepted_tos": false
  }
}
