{
  "id": "u-vmeJcJ-Z4",
  "created_at": "2018-02-18T09:52:23-05:00",
  "updated_at": "2019-09-21T01:03:36-04:00",
  "width": 3280,
  "height": 4928,
  "color": "#BDC99D",
  "description": null,
  "alt_description": "palm trees",
  "urls": {
    "raw": "https://images.unsplash.com/photo-1518965539400-77d851d65c43?ixlib=rb-1.2.1&ixid=eyJhcHBfaWQiOjkzMTQ3fQ",
    "full": "https://images.unsplash.com/photo-1518965539400-77d851d65c43?ixlib=rb-1.2.1&q=85&fm=jpg&crop=entropy&cs=srgb&ixid=eyJhcHBfaWQiOjkzMTQ3fQ",
    "regular": "https://images.unsplash.com/photo-1518965539400-77d851d65c43?ixlib=rb-1.2.1&q=80&fm=jpg&crop=entropy&cs=tinysrgb&w=1080&fit=max&ixid=eyJhcHBfaWQiOjkzMTQ3fQ",
    "small": "https://images.unsplash.com/photo-1518965539400-77d851d65c43?ixlib=rb-1.2.1&q=80&fm=jpg&crop=entropy&cs=tinysrgb&w=400&fit=max&ixid=eyJhcHBfaWQiOjkzMTQ3fQ",
    "thumb": "https://images.unsplash.com/photo-1518965539400-77d851d65c43?ixlib=rb-1.2.1&q=80&fm=jpg&crop=entropy&cs=tinysrgb&w=200&fit=max&ixid=eyJhcHBfaWQiOjkzMTQ3fQ"
  },
  "links": {
    "self": "https://api.unsplash.com/photos/u-vmeJcJ-Z4",
    "html": "https://unsplash.com/photos/u-vmeJcJ-Z4",
    "download": "https://unsplash.com/photos/u-vmeJcJ-Z4/download",
    "download_location": "https://api.unsplash.com/photos/u-vmeJcJ-Z4/download"
  },
  "categories": [],
  "likes": 1045,
  "liked_by_user": false,
  "current_user_collections": [],
  "user": {
    "id": "vsZait6dtqc",
    "updated_at": "2019-09-24T13:20:50-04:00",
    "username": "chuttersnap",
    "name": "chuttersnap",
    "first_name": "chuttersnap",
    "last_name": null,
    "twitter_username": null,
    "portfolio_url": "http://www.chuttersnap.com",
    "bio": "Unsplash Ambassador // The CHUTTERSNAP Empire",
    "location": "Singapore",
    "links": {
      "self": "https://api.unsplash.com/users/chuttersnap",
      "html": "https://unsplash.com/@chuttersnap",
      "photos": "https://api.unsplash.com/users/chuttersnap/photos",
      "likes": "https://api.unsplash.com/users/chuttersnap/likes",
      "portfolio": "https://api.unsplash.com/users/chuttersnap/portfolio",
      "following": "https://api.unsplash.com/users/chuttersnap/following",
      "followers": "https://api.unsplash.com/users/chuttersnap/followers"
    },
    "profile_image": {
      "small": "https://images.unsplash.com/profile-1519037305094-44617d4cf506?ixlib=rb-1.2.1&q=80&fm=jpg&crop=faces&cs=tinysrgb&fit=crop&h=32&w=32",
      "medium": "https://images.unsplash.com/profile-1519037305094-44617d4cf506?ixlib=rb-1.2.1&q=80&fm=jpg&crop=faces&cs=tinysrgb&fit=crop&h=64&w=64",
      "large": "https://images.unsplash.com/profile-1519037305094-44617d4cf506?ixlib=rb-1.2.1&q=80&fm=jpg&crop=faces&cs=tinysrgb&fit=crop&h=128&w=128"
    },
    "instagram_username": "chuttersnap",
    "total_collections": 1,
    "total_likes": 1351,
    "total_photos": 2471,
    "accepted_tos": true
  }
}
